mltlk/__init__.py
mltlk/embeddings.py
mltlk/exploration_tabdata.py
mltlk/exploration_textdata.py
mltlk/ml.py
mltlk/resampling.py
mltlk/utils.py
mltlk/word2vec.py
mltlk-0.1.39.dist-info/LICENSE
mltlk-0.1.39.dist-info/METADATA
mltlk-0.1.39.dist-info/WHEEL
mltlk-0.1.39.dist-info/top_level.txt
mltlk-0.1.39.dist-info/RECORD
