Metadata-Version: 2.1
Name: mltlk
Version: 0.1.39
Summary: Toolkit for making machine learning easier
Author: Johan Hagelbäck
Author-email: johan.hagelback@gmail.com
License-File: LICENSE
Requires-Dist: termcolor
Requires-Dist: scikit-learn
Requires-Dist: pandas
Requires-Dist: imblearn
Requires-Dist: gensim
Requires-Dist: customized-table
Requires-Dist: matplotlib
Requires-Dist: nltk
